myreplitdb/__init__.py
myreplitdb/database.py
myreplitdb/errors.py
MyReplitDB-1.2.dist-info/METADATA
MyReplitDB-1.2.dist-info/WHEEL
MyReplitDB-1.2.dist-info/top_level.txt
MyReplitDB-1.2.dist-info/RECORD
